kval/__init__.py
kval/calc/number.py
kval/data/__init__.py
kval/data/ctd.py
kval/data/dataset.py
kval/data/edit.py
kval/data/moored.py
kval/data/moored_tools/_compare_moored_prof.py
kval/data/moored_tools/_moored_decorator.py
kval/data/moored_tools/_moored_tools.py
kval/data/ship_ctd_tools/__init__.py
kval/data/ship_ctd_tools/_ctd_decorator.py
kval/data/ship_ctd_tools/_ctd_edit.py
kval/data/ship_ctd_tools/_ctd_tools.py
kval/data/ship_ctd_tools/_ctd_visualize.py
kval/file/__init__.py
kval/file/_variable_defs.py
kval/file/matfile.py
kval/file/rbr.py
kval/file/sbe.py
kval/geo/geocalc.py
kval/maps/maptools.py
kval/maps/quickmap.py
kval/metadata/__init__.py
kval/metadata/_standard_attrs.py
kval/metadata/_standard_attrs_org.py
kval/metadata/check_conventions.py
kval/metadata/conventionalize.py
kval/metadata/io.py
kval/ocean/empirical.py
kval/ocean/uv.py
kval/signal/despike.py
kval/signal/filt.py
kval/signal/interp.py
kval/signal/spec.py
kval/util/era5.py
kval/util/index.py
kval/util/internals.py
kval/util/magdec.py
kval/util/time.py
kval/util/user_input.py
kval/util/xr_funcs.py
kval-0.4.0.dist-info/METADATA
kval-0.4.0.dist-info/WHEEL
kval-0.4.0.dist-info/licenses/LICENSE
kval-0.4.0.dist-info/RECORD
