Metadata-Version: 2.4
Name: kval
Version: 0.4.0
Summary: Processing and analysis of ocean data in Python
Project-URL: Homepage, https://github.com/NPIOcean/kval/
Author-email: Øyvind Foss <oyvind.foss@npolar.no>, Tore Hattermann <tore.hattermann@npolar.no>
Maintainer: Norwegian Polar Institute, Oceanography section
Maintainer-email: "Øyvind Foss, NPI" <oyvind.foss@npolar.no>
License-Expression: MIT
License-File: LICENSE
Classifier: Development Status :: 2 - Pre-Alpha
Classifier: License :: OSI Approved :: MIT License
Classifier: Programming Language :: Python :: 3 :: Only
Classifier: Programming Language :: Python :: 3.10
Classifier: Programming Language :: Python :: 3.11
Classifier: Programming Language :: Python :: 3.12
Classifier: Programming Language :: Python :: 3.13
Classifier: Topic :: Scientific/Engineering :: Oceanography
Requires-Python: >=3.10
Requires-Dist: cartopy>=0.21.1
Requires-Dist: cftime>=1.6.2
Requires-Dist: cmocean>=3.0.3
Requires-Dist: compliance-checker>=5.1.0
Requires-Dist: glob2>=0.7
Requires-Dist: ipykernel>=6.26.0
Requires-Dist: ipympl>=0.9.3
Requires-Dist: jupyter>=1.0.0
Requires-Dist: matplotlib>=3.7.2
Requires-Dist: numpy>=1.23
Requires-Dist: pandas>=2.1.0
Requires-Dist: pygeomag>=1.1.0
Requires-Dist: pyrsktools>=1.1.1
Requires-Dist: ruamel-yaml>=0.18.15
Requires-Dist: scipy>=1.11.3
Requires-Dist: tqdm>=4.66.1
Requires-Dist: xarray>=2023.10.1
Requires-Dist: xlrd>=2.0.1
Provides-Extra: compliance
Provides-Extra: dev
Requires-Dist: pytest>=8.1.1; extra == 'dev'
